quote_manager/__init__.py
quote_manager-0.4.0.dist-info/WHEEL
quote_manager-0.4.0.dist-info/METADATA
quote_manager-0.4.0.dist-info/RECORD
