Metadata-Version: 2.1
Name: quote-manager
Version: 0.4.0
Summary: Helper nlp library for handling non ascii quotes.
License: Proprietary
Author: Sam Havens
Author-email: sam.havens@writer.com
Requires-Python: >=3.8,<4.0
Classifier: License :: Other/Proprietary License
Classifier: Programming Language :: Python :: 3
Classifier: Programming Language :: Python :: 3.8
Classifier: Programming Language :: Python :: 3.9
Requires-Dist: diff-match-patch (>=20181111,<20181112)
